DEPENDENCIES
INSTALL
LICENSE
README
ez_setup.py
setup.py
PDIS_XPath.egg-info/PKG-INFO
PDIS_XPath.egg-info/SOURCES.txt
PDIS_XPath.egg-info/dependency_links.txt
PDIS_XPath.egg-info/namespace_packages.txt
PDIS_XPath.egg-info/requires.txt
PDIS_XPath.egg-info/top_level.txt
pdis/__init__.py
pdis/xpath/__init__.py
pdis/xpath/atoms.py
pdis/xpath/bench.py
pdis/xpath/context.py
pdis/xpath/data_model.py
pdis/xpath/evaluate.py
pdis/xpath/lexer.py
pdis/xpath/parser.py
pdis/xpath/syntax.py
pdis/xpath/xpath_exceptions.py
pdis/xpath/tests/__init__.py
pdis/xpath/tests/test_evaluate.py
pdis/xpath/tests/test_parser.py
