Metadata-Version: 1.0
Name: PDIS-XPath
Version: 0.3
Summary: Pure-Python XPath evaluator based on ElementTree
Home-page: http://pdis.hiit.fi/pdis/download/
Author: Ken Rimey
Author-email: rimey@hiit.fi
License: MIT License
Platform: UNKNOWN
